openclassifier/__init__.py
openclassifier/_http.py
openclassifier/classify.py
openclassifier/client.py
openclassifier/exceptions.py
openclassifier/py.typed
openclassifier/types.py
openclassifier-0.1.0.dist-info/METADATA
openclassifier-0.1.0.dist-info/WHEEL
openclassifier-0.1.0.dist-info/licenses/LICENSE
openclassifier-0.1.0.dist-info/RECORD
