Metadata-Version: 2.4
Name: openclassifier
Version: 0.1.0
Summary: Python SDK for OpenClassifier - Ultra fast classification API
Project-URL: Homepage, https://github.com/openclassifier/openclassifier-python
Project-URL: Documentation, https://docs.openclassifier.com
Project-URL: Repository, https://github.com/openclassifier/openclassifier-python
Author: OpenClassifier
License-Expression: Apache-2.0
License-File: LICENSE
Keywords: api,classification,image-classification,pdf-classification,sdk,text-classification
Classifier: Development Status :: 4 - Beta
Classifier: Intended Audience :: Developers
Classifier: License :: OSI Approved :: Apache Software License
Classifier: Programming Language :: Python :: 3
Classifier: Programming Language :: Python :: 3.8
Classifier: Programming Language :: Python :: 3.9
Classifier: Programming Language :: Python :: 3.10
Classifier: Programming Language :: Python :: 3.11
Classifier: Programming Language :: Python :: 3.12
Classifier: Programming Language :: Python :: 3.13
Classifier: Typing :: Typed
Requires-Python: >=3.8
Requires-Dist: httpx>=0.25.0
Requires-Dist: typing-extensions>=4.0.0; python_version < '3.11'
Provides-Extra: dev
Requires-Dist: mypy>=1.0.0; extra == 'dev'
Requires-Dist: pytest>=7.0.0; extra == 'dev'
Requires-Dist: python-dotenv>=1.0.0; extra == 'dev'
Requires-Dist: ruff>=0.1.0; extra == 'dev'
